querymind/__init__.py
querymind/core.py
querymind/llms/__init__.py
querymind/llms/anthropic_llm.py
querymind/llms/base.py
querymind/llms/openai_llm.py
querymind-0.1.1.dist-info/licenses/LICENSE
querymind-0.1.1.dist-info/METADATA
querymind-0.1.1.dist-info/WHEEL
querymind-0.1.1.dist-info/top_level.txt
querymind-0.1.1.dist-info/RECORD
