Metadata-Version: 2.4
Name: querymind
Version: 0.1.1
Summary: Ask natural language questions about your CSV data using AI
Home-page: https://github.com/ra-is/querymind
Author: Ra-Is
Author-email: osumanurais@gmail.com
Project-URL: Bug Reports, https://github.com/ra-is/querymind/issues
Project-URL: Source, https://github.com/ra-is/querymind
Keywords: pandas,ai,llm,openai,anthropic,data-analysis,natural-language
Classifier: Development Status :: 3 - Alpha
Classifier: Intended Audience :: Developers
Classifier: Intended Audience :: Science/Research
Classifier: License :: OSI Approved :: MIT License
Classifier: Operating System :: OS Independent
Classifier: Programming Language :: Python :: 3
Classifier: Programming Language :: Python :: 3.8
Classifier: Programming Language :: Python :: 3.9
Classifier: Programming Language :: Python :: 3.10
Classifier: Programming Language :: Python :: 3.11
Classifier: Topic :: Scientific/Engineering
Classifier: Topic :: Software Development :: Libraries :: Python Modules
Requires-Python: >=3.8
License-File: LICENSE
Requires-Dist: pandas>=1.3.0
Requires-Dist: openai>=1.0.0
Requires-Dist: anthropic>=0.5.0
Dynamic: author
Dynamic: author-email
Dynamic: classifier
Dynamic: description
Dynamic: description-content-type
Dynamic: home-page
Dynamic: keywords
Dynamic: license-file
Dynamic: project-url
Dynamic: requires-dist
Dynamic: requires-python
Dynamic: summary
